{
  "project_info": {
    "project_number": "334087903719",
    "project_id": "local",
    "storage_bucket": "local.appspot.com"
  },
  "client": [
    {
      "client_info": {
        "mobilesdk_app_id": "1:334087903719:android:277f0bf3c1887739f40542",
        "android_client_info": {
          "package_name": "org.groundplatform.android"
        }
      },
      "oauth_client": [
        {
          "client_id": "local.apps.googleusercontent.com",
          "client_type": 3
        }
      ],
      "api_key": [
        {
          "current_key": "AIzaSyBKXBjsrQzgpbhgP9RwuOG6xWww83eKi_Q"
        }
      ],
      "services": {
        "appinvite_service": {
          "other_platform_oauth_client": []
        }
      }
    }
  ],
  "configuration_version": "1"
}